gecosistema_mail/__init__.py
gecosistema_mail/module.py
gecosistema_mail-0.0.10.dist-info/LICENSE
gecosistema_mail-0.0.10.dist-info/METADATA
gecosistema_mail-0.0.10.dist-info/WHEEL
gecosistema_mail-0.0.10.dist-info/top_level.txt
gecosistema_mail-0.0.10.dist-info/RECORD
