Metadata-Version: 2.1
Name: gecosistema-mail
Version: 0.0.10
Summary: A core functions package
Home-page: https://github.com/valluzzi/gecosistema_mail.git
Author: Valerio Luzzi
Author-email: valluzzi@gmail.com
License: UNKNOWN
Platform: UNKNOWN
Classifier: Programming Language :: Python :: 3
Classifier: License :: OSI Approved :: MIT License
Classifier: Operating System :: OS Independent
Requires-Dist: gecosistema-core
